LICENSE
README.md
setup.cfg
setup.py
megaetl/__init__.py
megaetl.egg-info/PKG-INFO
megaetl.egg-info/SOURCES.txt
megaetl.egg-info/dependency_links.txt
megaetl.egg-info/requires.txt
megaetl.egg-info/top_level.txt
megaetl/hooks/__init__.py
megaetl/hooks/dremio_hook.py
megaetl/hooks/mssql_hook.py
megaetl/hooks/postgres_hook.py
megaetl/hooks/sap_hook.py
megaetl/operators/__init__.py
megaetl/operators/db_2_s3_operator.py
megaetl/operators/sap_2_db_operator.py
megaetl/util/__init__.py
megaetl/util/convert_helpers.py