Metadata-Version: 2.1
Name: megaetl
Version: 0.0.1
Summary: Airflow plugins
Home-page: https://github.com/victorouttes/MegaETL
Author: Victor Outtes
Author-email: victor.outtes@gmail.com
License: MIT
Download-URL: https://github.com/victorouttes/MegaETL/archive/refs/tags/0.0.1.tar.gz
Keywords: airflow,plugins
Platform: UNKNOWN
Classifier: Development Status :: 3 - Alpha
Classifier: Intended Audience :: Developers
Classifier: Topic :: Software Development :: Build Tools
Classifier: License :: OSI Approved :: MIT License
Classifier: Programming Language :: Python :: 3
Classifier: Programming Language :: Python :: 3.4
Classifier: Programming Language :: Python :: 3.5
Classifier: Programming Language :: Python :: 3.6
License-File: LICENSE
